python_ace-0.2.8.dist-info/top_level.txt
python_ace-0.2.8.dist-info/WHEEL
python_ace-0.2.8.dist-info/RECORD
python_ace-0.2.8.dist-info/METADATA
python_ace-0.2.8.dist-info/LICENSE.md
python_ace-0.2.8.data/scripts/pace_timing
python_ace-0.2.8.data/scripts/pacemaker
python_ace-0.2.8.data/scripts/pace_update_ace
python_ace-0.2.8.data/scripts/pace_info
python_ace-0.2.8.data/scripts/pace_update_yaml_potential
python_ace-0.2.8.data/scripts/pace_yaml2yace
python_ace-0.2.8.data/scripts/pace_collect
pyace/calculator.cpython-39-x86_64-linux-gnu.so
pyace/paralleldataexecutor.py
pyace/preparedata.py
pyace/sharmonics.cpython-39-x86_64-linux-gnu.so
pyace/const.py
pyace/generalfit.py
pyace/pyacefit.py
pyace/fitadapter.py
pyace/radial.py
pyace/libyaml-cpp-pace.so.0.6.3
pyace/evaluator.cpython-39-x86_64-linux-gnu.so
pyace/lossfuncspec.py
pyace/coupling.cpython-39-x86_64-linux-gnu.so
pyace/helpers.py
pyace/_version.py
pyace/pyneighbor.py
pyace/atomicenvironment.py
pyace/fitcallbacks.py
pyace/read_base_conf.py
pyace/basis.cpython-39-x86_64-linux-gnu.so
pyace/metrics_aggregator.py
pyace/validate.py
pyace/asecalc.py
pyace/basisextension.py
pyace/catomicenvironment.cpython-39-x86_64-linux-gnu.so
pyace/multispecies_basisextension.py
pyace/libyaml-cpp-pace.so.0.6
pyace/libyaml-cpp-pace.so
pyace/__init__.py
pyace/utils/timing.py
pyace/utils/__init__.py
pyace/ace/__init__.py
pyace/data/mus_ns_uni_to_rawlsLS_np_rank.pckl
pyace/data/input_template.yaml
pyace/data/__init__.py
