Metadata-Version: 2.1
Name: python-ace
Version: 0.2.8
Summary: Python bindings, utilities  for PACE and fitting code "pacemaker"
Home-page: https://github.com/ICAMS/python-ace
Author: Yury Lysogorskiy, Anton Bochkarev, Sarath Menon, Ralf Drautz
Author-email: yury.lysogorskiy@rub.de
Classifier: Programming Language :: Python :: 3
License-File: LICENSE.md
Requires-Dist: numpy
Requires-Dist: ase
Requires-Dist: pandas
Requires-Dist: ruamel.yaml
